moveread/pipelines/reorder/__init__.py
moveread/pipelines/reorder/__init__.pyi
moveread/pipelines/reorder/pipeline.py
moveread/pipelines/reorder/types.py
moveread/pipelines/reorder/scripts/cli.py
moveread/pipelines/reorder/scripts/clientgen.py
moveread_pipelines_reorder-0.1.1.dist-info/METADATA
moveread_pipelines_reorder-0.1.1.dist-info/WHEEL
moveread_pipelines_reorder-0.1.1.dist-info/entry_points.txt
moveread_pipelines_reorder-0.1.1.dist-info/top_level.txt
moveread_pipelines_reorder-0.1.1.dist-info/RECORD
