Metadata-Version: 2.1
Name: moveread-pipelines-reorder
Version: 0.1.1
Author-email: Marcel Claramunt <marcel@moveread.com>
Project-URL: repo, https://github.com/moveread/pipelines.git
Requires-Python: >=3.10
Requires-Dist: pipeteer
Requires-Dist: fastapi
